{
  "metrics": {
    "fusion_method": "gating",
    "best_epoch": 13,
    "epochs_run": 21,
    "train_seconds": 17.2,
    "val": {
      "loss": 0.15095912976233836,
      "accuracy": 0.9729144095341279,
      "macro_f1": 0.9651805330886791
    },
    "val_per_class": {
      "human": {
        "precision": 0.9566115702479339,
        "recall": 0.9410569105691057,
        "f1": 0.9487704918032787
      },
      "ai": {
        "precision": 0.9787077826725403,
        "recall": 0.9844903988183161,
        "f1": 0.9815905743740795
      }
    }
  },
  "history": [
    {
      "epoch": 1,
      "train": {
        "loss": 0.2172034095074123,
        "accuracy": 0.8996222342147868,
        "macro_f1": 0.877938751572434
      },
      "val": {
        "loss": 0.10336900792636566,
        "accuracy": 0.9555796316359697,
        "macro_f1": 0.944660141643598
      }
    },
    {
      "epoch": 2,
      "train": {
        "loss": 0.08870303873606006,
        "accuracy": 0.9661090124123044,
        "macro_f1": 0.9568652566108082
      },
      "val": {
        "loss": 0.08950341967532849,
        "accuracy": 0.9609967497291441,
        "macro_f1": 0.951114014335652
      }
    },
    {
      "epoch": 3,
      "train": {
        "loss": 0.047032942576660575,
        "accuracy": 0.9821910415542364,
        "macro_f1": 0.9771670244650578
      },
      "val": {
        "loss": 0.09925013850014233,
        "accuracy": 0.9696641386782232,
        "macro_f1": 0.9613048894425413
      }
    },
    {
      "epoch": 4,
      "train": {
        "loss": 0.0348759803157531,
        "accuracy": 0.9873718294657312,
        "macro_f1": 0.9837372802752047
      },
      "val": {
        "loss": 0.11750491555550116,
        "accuracy": 0.9664138678223185,
        "macro_f1": 0.9575377126787318
      }
    },
    {
      "epoch": 5,
      "train": {
        "loss": 0.02273758577137152,
        "accuracy": 0.9915812196438208,
        "macro_f1": 0.9891194595921478
      },
      "val": {
        "loss": 0.09969404577817424,
        "accuracy": 0.9691224268689057,
        "macro_f1": 0.9610351665564992
      }
    },
    {
      "epoch": 6,
      "train": {
        "loss": 0.0184180800782399,
        "accuracy": 0.9934160820291419,
        "macro_f1": 0.991478404567472
      },
      "val": {
        "loss": 0.13854755814195302,
        "accuracy": 0.9685807150595883,
        "macro_f1": 0.9596623129633062
      }
    },
    {
      "epoch": 7,
      "train": {
        "loss": 0.01489766202655938,
        "accuracy": 0.9946033459255261,
        "macro_f1": 0.9930066917166742
      },
      "val": {
        "loss": 0.14458456858467889,
        "accuracy": 0.9664138678223185,
        "macro_f1": 0.9572138857112951
      }
    },
    {
      "epoch": 8,
      "train": {
        "loss": 0.010697796460045315,
        "accuracy": 0.9965461413923368,
        "macro_f1": 0.9955218874096644
      },
      "val": {
        "loss": 0.14936402844232816,
        "accuracy": 0.9669555796316359,
        "macro_f1": 0.9575480998508985
      }
    },
    {
      "epoch": 9,
      "train": {
        "loss": 0.0055908037074343985,
        "accuracy": 0.9982730706961683,
        "macro_f1": 0.997758541312394
      },
      "val": {
        "loss": 0.1497368996028051,
        "accuracy": 0.9680390032502708,
        "macro_f1": 0.9587773471844838
      }
    },
    {
      "epoch": 10,
      "train": {
        "loss": 0.003867011811549115,
        "accuracy": 0.9988127361036158,
        "macro_f1": 0.9984579615566631
      },
      "val": {
        "loss": 0.1315132819963942,
        "accuracy": 0.9707475622968581,
        "macro_f1": 0.962590517707245
      }
    },
    {
      "epoch": 11,
      "train": {
        "loss": 0.0035983901290653733,
        "accuracy": 0.9987048030221263,
        "macro_f1": 0.9983170970587252
      },
      "val": {
        "loss": 0.14729097493261276,
        "accuracy": 0.9707475622968581,
        "macro_f1": 0.9623949757357735
      }
    },
    {
      "epoch": 12,
      "train": {
        "loss": 0.002299148736993294,
        "accuracy": 0.9992444684295737,
        "macro_f1": 0.9990184387465746
      },
      "val": {
        "loss": 0.14819125170776073,
        "accuracy": 0.9723726977248104,
        "macro_f1": 0.9645074277441938
      }
    },
    {
      "epoch": 13,
      "train": {
        "loss": 0.0015499766402659486,
        "accuracy": 0.9996762007555315,
        "macro_f1": 0.9995789907110006
      },
      "val": {
        "loss": 0.15095912976233836,
        "accuracy": 0.9729144095341279,
        "macro_f1": 0.9651805330886791
      }
    },
    {
      "epoch": 14,
      "train": {
        "loss": 0.0034549164418025565,
        "accuracy": 0.9985968699406368,
        "macro_f1": 0.9981775909306019
      },
      "val": {
        "loss": 0.1600394623905505,
        "accuracy": 0.9712892741061755,
        "macro_f1": 0.9630184151948131
      }
    },
    {
      "epoch": 15,
      "train": {
        "loss": 0.0015993452841527578,
        "accuracy": 0.9996762007555315,
        "macro_f1": 0.9995791042165671
      },
      "val": {
        "loss": 0.19666550494642185,
        "accuracy": 0.9685807150595883,
        "macro_f1": 0.9591214322694348
      }
    },
    {
      "epoch": 16,
      "train": {
        "loss": 0.003609992596591585,
        "accuracy": 0.9987048030221263,
        "macro_f1": 0.9983170970587252
      },
      "val": {
        "loss": 0.20250929080321678,
        "accuracy": 0.9685807150595883,
        "macro_f1": 0.9592317592317592
      }
    },
    {
      "epoch": 17,
      "train": {
        "loss": 0.003241163533296802,
        "accuracy": 0.9989206691851052,
        "macro_f1": 0.9985979583004199
      },
      "val": {
        "loss": 0.16421880589620003,
        "accuracy": 0.9712892741061755,
        "macro_f1": 0.9631637780790632
      }
    },
    {
      "epoch": 18,
      "train": {
        "loss": 0.0022501373913463786,
        "accuracy": 0.9989206691851052,
        "macro_f1": 0.9985972030909559
      },
      "val": {
        "loss": 0.16779252980106216,
        "accuracy": 0.971830985915493,
        "macro_f1": 0.9635471018290247
      }
    },
    {
      "epoch": 19,
      "train": {
        "loss": 0.0012398544068972712,
        "accuracy": 0.999568267674042,
        "macro_f1": 0.9994387299704142
      },
      "val": {
        "loss": 0.15998797293740827,
        "accuracy": 0.9729144095341279,
        "macro_f1": 0.9651347092091207
      }
    },
    {
      "epoch": 20,
      "train": {
        "loss": 0.0015417885150498054,
        "accuracy": 0.9994603345925526,
        "macro_f1": 0.9992986960166433
      },
      "val": {
        "loss": 0.17667114211149632,
        "accuracy": 0.9729144095341279,
        "macro_f1": 0.9649491363740622
      }
    },
    {
      "epoch": 21,
      "train": {
        "loss": 0.001517998578048063,
        "accuracy": 0.999568267674042,
        "macro_f1": 0.9994387299704142
      },
      "val": {
        "loss": 0.16278448550722144,
        "accuracy": 0.971830985915493,
        "macro_f1": 0.9637877544122262
      }
    }
  ]
}